aat_downloader/__init__.py
aat_downloader/_nbdev.py
aat_downloader/downloader.py
aat_downloader-0.0.4.dist-info/LICENSE
aat_downloader-0.0.4.dist-info/METADATA
aat_downloader-0.0.4.dist-info/WHEEL
aat_downloader-0.0.4.dist-info/entry_points.txt
aat_downloader-0.0.4.dist-info/top_level.txt
aat_downloader-0.0.4.dist-info/RECORD
