Metadata-Version: 2.1
Name: aat-downloader
Version: 0.0.4
Summary: A downloader for mobile aat data.
Home-page: https://github.com/hgzech/aat_downloader/tree/master/
Author: Hilmar Zech
Author-email: hgzech@gmail.com
License: Apache Software License 2.0
Keywords: mobile aat download downloader
Platform: UNKNOWN
Classifier: Development Status :: 3 - Alpha
Classifier: Intended Audience :: Developers
Classifier: Natural Language :: English
Classifier: Programming Language :: Python :: 3.6
Classifier: Programming Language :: Python :: 3.7
Classifier: Programming Language :: Python :: 3.8
Classifier: License :: OSI Approved :: Apache Software License
Requires-Python: >=3.6
License-File: LICENSE
Requires-Dist: pip
Requires-Dist: packaging
Requires-Dist: pyrebase4
Requires-Dist: pandas
Provides-Extra: dev
